mug/__init__.py
mug/cli/__init__.py
mug/cli/__main__.py
mug/common/__init__.py
mug/common/application/__init__.py
mug/common/domain/__init__.py
mug/common/infrastructure/__init__.py
mug/common/presentation/__init__.py
mug/modules/__init__.py
mug/modules/documents/__init__.py
mug/modules/documents/application/__init__.py
mug/modules/documents/domain/__init__.py
mug/modules/documents/infrastructure/__init__.py
mug/modules/documents/presentation/__init__.py
mug/modules/system/__init__.py
mug/modules/system/application/__init__.py
mug/modules/system/domain/__init__.py
mug/modules/system/infrastructure/__init__.py
mug/modules/system/presentation/__init__.py
mug-0.3.0.dist-info/METADATA
mug-0.3.0.dist-info/WHEEL
mug-0.3.0.dist-info/entry_points.txt
mug-0.3.0.dist-info/licenses/LICENSE
mug-0.3.0.dist-info/RECORD
