Metadata-Version: 2.4
Name: mug
Version: 0.3.0
Summary: XML Schema (XSD 1.0/1.1) validation CLI.
Project-URL: Homepage, https://github.com/bynbb/mug
Project-URL: Repository, https://github.com/bynbb/mug
Project-URL: Issues, https://github.com/bynbb/mug/issues
License: MIT License
License-File: LICENSE
Classifier: License :: OSI Approved :: MIT License
Classifier: Programming Language :: Python :: 3
Classifier: Programming Language :: Python :: 3 :: Only
Classifier: Programming Language :: Python :: 3.11
Requires-Python: >=3.11
Provides-Extra: test
Requires-Dist: import-linter>=2.0; extra == 'test'
Requires-Dist: pytest-cov>=4.1; extra == 'test'
Requires-Dist: pytest>=8.0; extra == 'test'
Requires-Dist: pyyaml>=6.0; extra == 'test'
Requires-Dist: ruff>=0.4; extra == 'test'
